[
    {
        "name": "-所有地级市-",
        "value": "-1",
        "level": 2,
        "memo": "河南省"
    },
    {
        "name": "郑州市",
        "value": "410100000000",
        "level": 3
    },
    {
        "name": "开封市",
        "value": "410200000000",
        "level": 3
    },
    {
        "name": "洛阳市",
        "value": "410300000000",
        "level": 3
    },
    {
        "name": "平顶山市",
        "value": "410400000000",
        "level": 3
    },
    {
        "name": "安阳市",
        "value": "410500000000",
        "level": 3
    },
    {
        "name": "鹤壁市",
        "value": "410600000000",
        "level": 3
    },
    {
        "name": "新乡市",
        "value": "410700000000",
        "level": 3
    },
    {
        "name": "焦作市",
        "value": "410800000000",
        "level": 3
    },
    {
        "name": "濮阳市",
        "value": "410900000000",
        "level": 3
    },
    {
        "name": "许昌市",
        "value": "411000000000",
        "level": 3
    },
    {
        "name": "漯河市",
        "value": "411100000000",
        "level": 3
    },
    {
        "name": "三门峡市",
        "value": "411200000000",
        "level": 3
    },
    {
        "name": "南阳市",
        "value": "411300000000",
        "level": 3
    },
    {
        "name": "商丘市",
        "value": "411400000000",
        "level": 3
    },
    {
        "name": "信阳市",
        "value": "411500000000",
        "level": 3
    },
    {
        "name": "周口市",
        "value": "411600000000",
        "level": 3
    },
    {
        "name": "驻马店市",
        "value": "411700000000",
        "level": 3
    },
    {
        "name": "济源市",
        "value": "419000000000",
        "level": 3
    }
]